README.txt
setup.py
ia636/iaapplylut.py
ia636/iabwlp.py
ia636/iacircle.py
ia636/iacolorhist.py
ia636/iacolormap.py
ia636/iacomb.py
ia636/iacontour.py
ia636/iaconv.py
ia636/iacorr.py
ia636/iacos.py
ia636/iacrop.py
ia636/iadct.py
ia636/iadctmatrix.py
ia636/iadft.py
ia636/iadftmatrix.py
ia636/iadftview.py
ia636/iadither.py
ia636/iaellipse.py
ia636/iaffine.py
ia636/iaffine3.py
ia636/iafftshift.py
ia636/iafig2img.py
ia636/iafloyd.py
ia636/iaftemplate.py
ia636/iagaussian.py
ia636/iageorigid.py
ia636/iagshow.py
ia636/iah2percentile.py
ia636/iah2stats.py
ia636/iahaarmatrix.py
ia636/iahadamard.py
ia636/iahadamardmatrix.py
ia636/iahistogram.py
ia636/iahwt.py
ia636/iaidct.py
ia636/iaidft.py
ia636/iaifftshift.py
ia636/iaihadamard.py
ia636/iaihwt.py
ia636/iaimginfo.py
ia636/iaind2sub.py
ia636/iainterpolclosest.py
ia636/iainterpollin.py
ia636/iaisdftsym.py
ia636/iaisolines.py
ia636/ialblshow.py
ia636/ialog.py
ia636/ialogfilter.py
ia636/iameshgrid.py
ia636/iamosaic.py
ia636/ianeg.py
ia636/ianormalize.py
ia636/ianshow.py
ia636/iaotsu.py
ia636/iapad.py
ia636/iapca.py
ia636/iapconv.py
ia636/iapconv2.py
ia636/iapercentile.py
ia636/iaphasecorr.py
ia636/iaplot.py
ia636/iapolar.py
ia636/iaptrans.py
ia636/iaramp.py
ia636/iareadurl.py
ia636/iarectangle.py
ia636/iargb2gray.py
ia636/iaroi.py
ia636/iarot90.py
ia636/iasobel.py
ia636/iastat.py
ia636/iasub2ind.py
ia636/iatcrgb2ind.py
ia636/iatext.py
ia636/iatile.py
ia636/iatiling.py
ia636/iavarfilter.py
ia636/iawcorr.py
ia636.egg-info/PKG-INFO
ia636.egg-info/SOURCES.txt
ia636.egg-info/dependency_links.txt
ia636.egg-info/top_level.txt
images/__init__.py