Metadata-Version: 1.1
Name: ia636
Version: 0.11.6
Summary: Python Toolbox for Teaching Image Processing
Home-page: https://github.com/robertoalotufo/ia636
Author: Roberto A Lotufo and collaborators
Author-email: robertoalotufo@gmail.com
License: BSD 3 clauses
Keywords: image processing
Platform: UNKNOWN
Classifier: Development Status :: 4 - Beta
Classifier: Intended Audience :: Science/Research
Classifier: Programming Language :: Python :: 2 :: Only
Classifier: Topic :: Scientific/Engineering :: Image Recognition
Classifier: License :: OSI Approved :: BSD License
